pyjdk/__init__.py
pyjdk/pyjdk.py
pyjdk-1.0.1.dist-info/METADATA
pyjdk-1.0.1.dist-info/WHEEL
pyjdk-1.0.1.dist-info/top_level.txt
pyjdk-1.0.1.dist-info/RECORD
